CHANGELOG.txt
LICENCE.txt
MANIFEST.in
README.txt
setup.py
comphelper/__init__.py
comphelper.egg-info/PKG-INFO
comphelper.egg-info/SOURCES.txt
comphelper.egg-info/dependency_links.txt
comphelper.egg-info/requires.txt
comphelper.egg-info/top_level.txt