Metadata-Version: 2.1
Name: comphelper
Version: 0.0.4
Summary: Helps to view DataFrames
Home-page: UNKNOWN
Author: Nicholas Carrier
Author-email: nicholas.carrier.wm@gmail.com
License: MIT
Keywords: compensation
Platform: UNKNOWN
Classifier: Development Status :: 5 - Production/Stable
Classifier: Intended Audience :: Education
Classifier: Operating System :: Microsoft :: Windows :: Windows 10
Classifier: License :: OSI Approved :: MIT License
Classifier: Programming Language :: Python :: 3
License-File: LICENCE.txt
